spotml/__init__.py
spotml/cli.py
spotml/configuration.py
spotml/parser.py
spotml/utils.py
spotml/commands/__init__.py
spotml/commands/abstract_command.py
spotml/commands/abstract_config_command.py
spotml/commands/abstract_provider_command.py
spotml/commands/aws.py
spotml/commands/download.py
spotml/commands/exec.py
spotml/commands/handle_active_run.py
spotml/commands/handle_error_runs.py
spotml/commands/handle_scheduled_run.py
spotml/commands/run.py
spotml/commands/run_locally.py
spotml/commands/sh.py
spotml/commands/start.py
spotml/commands/status.py
spotml/commands/stop.py
spotml/commands/sync.py
spotml/commands/writers/__init__.py
spotml/commands/writers/abstract_output_writrer.py
spotml/commands/writers/null_output_writrer.py
spotml/commands/writers/output_writrer.py
spotml/config/__init__.py
spotml/config/abstract_instance_config.py
spotml/config/abstract_instance_volume.py
spotml/config/config_utils.py
spotml/config/container_config.py
spotml/config/host_path_volume.py
spotml/config/project_config.py
spotml/config/tmp_dir_volume.py
spotml/config/url.py
spotml/config/validation.py
spotml/constants/__init__.py
spotml/constants/constants.py
spotml/constants/run_status.py
spotml/deployment/__init__.py
spotml/deployment/abstract_docker_instance_manager.py
spotml/deployment/abstract_instance_manager.py
spotml/deployment/abstract_ssh_instance_manager.py
spotml/deployment/abstract_cloud_instance/__init__.py
spotml/deployment/abstract_cloud_instance/abstract_bucket_manager.py
spotml/deployment/abstract_cloud_instance/abstract_cloud_instance_manager.py
spotml/deployment/abstract_cloud_instance/abstract_data_transfer.py
spotml/deployment/abstract_cloud_instance/abstract_instance_deployment.py
spotml/deployment/abstract_cloud_instance/file_structure.py
spotml/deployment/abstract_cloud_instance/errors/__init__.py
spotml/deployment/abstract_cloud_instance/errors/bucket_not_found.py
spotml/deployment/abstract_cloud_instance/resources/__init__.py
spotml-0.0.11.dist-info/LICENSE
spotml-0.0.11.dist-info/METADATA
spotml-0.0.11.dist-info/WHEEL
spotml-0.0.11.dist-info/entry_points.txt
spotml-0.0.11.dist-info/top_level.txt
spotml-0.0.11.dist-info/RECORD
